memora/__init__.py
memora/agent/__init__.py
memora/agent/main.py
memora/graph_db/__init__.py
memora/graph_db/base.py
memora/graph_db/neo4j/__init__.py
memora/graph_db/neo4j/agent.py
memora/graph_db/neo4j/interaction.py
memora/graph_db/neo4j/interface.py
memora/graph_db/neo4j/memory.py
memora/graph_db/neo4j/organization.py
memora/graph_db/neo4j/user.py
memora/llm_backends/__init__.py
memora/llm_backends/azure_openai_backend_llm.py
memora/llm_backends/base.py
memora/llm_backends/groq_backend_llm.py
memora/llm_backends/openai_backend_llm.py
memora/llm_backends/together_backend_llm.py
memora/prompts/__init__.py
memora/prompts/filter_retrieved_memories.py
memora/prompts/memory_extraction.py
memora/prompts/memory_search_from_msg.py
memora/schema/__init__.py
memora/schema/extraction_schema.py
memora/schema/models.py
memora/schema/storage_schema.py
memora/vector_db/__init__.py
memora/vector_db/base.py
memora/vector_db/qdrant.py
memora_core-0.3.1.dist-info/LICENSE
memora_core-0.3.1.dist-info/METADATA
memora_core-0.3.1.dist-info/WHEEL
memora_core-0.3.1.dist-info/RECORD
