Metadata-Version: 2.1
Name: memora-core
Version: 0.3.1
Summary: Memora is an agent that aims to replicate the human memory for AI assistants / agents.
Home-page: https://github.com/ELZAI/memora
License: Apache-2.0
Author: ELZAI
Author-email: founders@elzai.com
Requires-Python: >=3.9,<4.0
Classifier: License :: OSI Approved :: Apache Software License
Classifier: Programming Language :: Python :: 3
Classifier: Programming Language :: Python :: 3.9
Classifier: Programming Language :: Python :: 3.10
Classifier: Programming Language :: Python :: 3.11
Classifier: Programming Language :: Python :: 3.12
Classifier: Programming Language :: Python :: 3.13
Requires-Dist: fastembed (>=0.5.0,<0.6.0)
Requires-Dist: groq (==0.13.1)
Requires-Dist: neo4j (==5.20.0)
Requires-Dist: neo4j-rust-ext (==5.20.0.0)
Requires-Dist: openai (==1.55.3)
Requires-Dist: pydantic (==2.10.4)
Requires-Dist: python-dotenv (==1.0.1)
Requires-Dist: qdrant-client (==1.12.1)
Requires-Dist: shortuuid (==1.0.13)
Requires-Dist: together (==1.3.10)
Requires-Dist: typing-extensions (==4.12.2)
Project-URL: Documentation, https://elzai.github.io/memora/
Project-URL: Repository, https://github.com/ELZAI/memora
